{
  "id" : null,
  "name" : "AAA_GOAL2",
  "boardTxt" : "I1(10)<ge*a>^0,J1(39)<km*e>^0,K1(60)<vq*m>^0,L1(26)<bi*q>^0,M1(21)<de*i>^0,N1(40)<si*e>^0,O1(22)<la*i>^0,P1(1)<aq**>^3,H2(111)<lojn>^1,I2(115)<gljk>^2,J2(224)<tgkk>^0,K2(184)<vgnc>^2,L2(70)<cgbc>^0,M2(175)<gufd>^3,N2(150)<fkrs>^3,O2(156)<glrd>^1,P2(30)<gm*q>^3,C3(208)<svck>^2,H3(62)<ngbb>^2,I3(67)<kjbr>^1,J3(231)<ltkh>^1,K3(196)<vonl>^0,L3(212)<cpco>^0,M3(254)<uptp>^2,N3(181)<kpfu>^2,O3(242)<dush>^2,P3(56)<hq*m>^3,H4(99)<ufbv>^0,I4(144)<uurf>^0,J4(160)<uurh>^3,K4(151)<dvrs>^1,L4(165)<cdfn>^2,M4(177)<ndft>^3,N4(140)<flrf>^3,O4(81)<srbo>^2,P4(31)<oi*q>^3,H5(216)<vucl>^1,I5(256)<uvhv>^2,J5(247)<uvoo>^2,K5(226)<sokg>^2,L5(171)<tpfg>^0,M5(164)<dprv>^2,N5(125)<lvjh>^2,O5(95)<lnbh>^0,P5(17)<nm*i>^3,G6(205)<pcnu>^2,H6(194)<uknl>^3,I6(204)<lhnu>^1,J6(110)<oljn>^2,K6(114)<ndjk>^3,L6(131)<ftju>^1,M6(138)<fcrf>^0,N6(113)<tpjc>^0,O6(102)<lpjj>^2,P6(50)<ja*m>^3,G7(203)<lsnu>^0,H7(153)<ksrg>^2,I7(182)<gkfu>^3,J7(109)<pkjf>^0,K7(83)<kdbd>^3,L7(80)<pubg>^1,M7(122)<fpjt>^2,N7(124)<tojt>^3,O7(104)<vfjj>^0,P7(7)<fa*a>^3,B8(253)<ptlh>^0,C8(236)<gtsd>^2,D8(73)<odbk>^2,E8(227)<llkg>^1,F8(238)<dpsl>^0,G8(87)<ptbl>^3,H8(82)<rrbd>^1,I8(139)<fkrf>^1,J8(178)<lpfh>^1,K8(218)<dlcp>^2,L8(180)<gpfp>^2,M8(129)<dcjp>^0,N8(211)<pocg>^1,O8(136)<ptjv>^3,P8(6)<ji*a>^3,A9(46)<te*e>^1,B9(130)<thjp>^3,C9(112)<tsjc>^1,D9(90)<dpbt>^0,E9(234)<pdsg>^3,F9(235)<gdsd>^1,G9(245)<vtgd>^1,H9(251)<vhdd>^3,I9(108)<dojf>^3,J9(106)<chjf>^1,K9(191)<ccno>^2,L9(173)<oofo>^0,M9(248)<ldod>^1,N9(71)<glbc>^2,O9(79)<tcbg>^2,P9(19)<gi*i>^3,A10(53)<ge*m>^1,B10(244)<thgo>^1,C10(214)<ctcl>^2,D10(237)<losd>^3,E10(97)<dsbv>^2,F10(215)<dvcl>^2,G10(252)<hldl>^0,H10(232)<lukh>^3,I10(163)<okrv>^2,J10(89)<fvbt>^2,K10(199)<ttnt>^0,L10(192)<otno>^2,M10(105)<dojr>^2,N10(64)<bhbr>^0,O10(91)<klbh>^0,P10(23)<lm*i>^3,A11(49)<bm*m>^1,B11(76)<nobs>^1,C11(148)<cnrc>^2,D11(209)<hock>^1,E11(93)<sdbh>^0,F11(145)<cdrn>^2,G11(198)<shnt>^1,H11(241)<gush>^1,I11(152)<kkrg>^0,J11(72)<nrbk>^0,K11(161)<ftrp>^1,L11(127)<nfjp>^2,M11(103)<psjj>^3,N11(63)<jcbj>^0,O11(167)<ccfk>^3,P11(52)<fa*m>^3,A12(18)<sm*i>^1,B12(233)<stss>^0,C12(159)<hfrt>^0,D12(172)<ukfg>^1,E12(141)<surf>^2,F12(142)<ofrf>^0,G12(174)<ltfo>^1,H12(86)<hlbl>^2,I12(116)<lkjk>^3,J12(132)<lnju>^1,K12(143)<plrf>^2,L12(107)<shjf>^0,M12(228)<shkd>^2,N12(121)<nvjd>^0,O12(221)<uucv>^0,P12(14)<ue*a>^3,A13(59)<ui*m>^1,B13(187)<ugns>^3,C13(201)<uhnp>^1,D13(246)<pvgu>^0,E13(69)<vhbr>^3,F13(92)<sobh>^1,G13(240)<uost>^1,H13(88)<bubt>^2,I13(229)<gvkt>^0,J13(222)<uvcv>^2,K13(147)<rvrc>^2,L13(200)<scnh>^2,M13(75)<hcbk>^3,N13(85)<fnbl>^1,O13(169)<sufs>^1,P13(41)<sq*e>^3,A14(38)<cm*e>^1,B14(207)<vgcc>^1,C14(255)<pvtv>^2,D14(202)<vgnp>^3,E14(186)<hhnk>^1,F14(179)<hofh>^3,G14(68)<tfbr>^2,H14(65)<rvbr>^0,I14(154)<vprg>^3,J14(146)<rlrc>^3,K14(137)<tgrr>^0,L14(188)<nung>^0,M14(219)<kdcu>^0,N14(249)<duol>^3,O14(217)<soct>^2,P14(32)<tq*q>^3,A15(48)<pe*e>^1,B15(78)<cpbg>^2,C15(158)<gprt>^3,D15(157)<vgrd>^1,E15(117)<vpjk>^3,F15(126)<uojh>^1,G15(96)<ucbu>^0,H15(149)<olrc>^0,I15(119)<pljg>^2,J15(243)<olgo>^1,K15(239)<ovst>^3,L15(123)<nsjt>^2,M15(74)<tobk>^3,N15(94)<dubh>^1,O15(213)<hhcd>^0,P15(33)<hi*q>^3,A16(2)<ae**>^1,B16(5)<ba*a>^2,C16(57)<pa*m>^2,D16(55)<dm*m>^2,E16(58)<pm*m>^2,F16(13)<hm*a>^2,G16(25)<ua*i>^2,H16(11)<oi*a>^2,I16(15)<ja*i>^2,J16(43)<oi*e>^2,K16(36)<ve*q>^2,L16(28)<jq*q>^2,M16(44)<oq*e>^2,N16(47)<he*e>^2,O16(34)<he*q>^2,P16(3)<iq**>^2",
  "createTS" : 1528441189480,
  "absoluteLevel" : 205
}