{
  "id" : null,
  "name" : "AAA_GOAL5",
  "boardTxt" : "I1(55)<dm*m>^0,J1(59)<ui*m>^0,K1(17)<nm*i>^0,L1(49)<bm*m>^0,M1(53)<ge*m>^0,N1(38)<cm*e>^0,O1(52)<fa*m>^0,P1(2)<ae**>^3,G2(96)<ucbu>^1,H2(247)<uvoo>^3,I2(105)<dojr>^2,J2(144)<uurf>^1,K2(204)<lhnu>^0,L2(95)<lnbh>^0,M2(184)<vgnc>^1,N2(220)<kpcv>^0,O2(180)<gpfp>^0,P2(48)<pe*e>^3,C3(208)<svck>^2,G3(242)<dush>^1,H3(135)<dcjv>^3,I3(102)<lpjj>^0,J3(143)<plrf>^3,K3(146)<rlrc>^1,L3(149)<olrc>^1,M3(212)<cpco>^0,N3(181)<kpfu>^2,O3(175)<gufd>^2,P3(45)<da*e>^3,G4(160)<uurh>^3,H4(138)<fcrf>^1,I4(85)<fnbl>^3,J4(86)<hlbl>^1,K4(106)<chjf>^2,L4(167)<ccfk>^1,M4(191)<ccno>^2,N4(174)<ltfo>^0,O4(131)<ftju>^2,P4(14)<ue*a>^3,G5(99)<ufbv>^2,H5(89)<fvbt>^2,I5(198)<shnt>^0,J5(253)<ptlh>^0,K5(123)<nsjt>^0,L5(153)<ksrg>^2,M5(188)<nung>^0,N5(194)<uknl>^3,O5(111)<lojn>^0,P5(42)<oa*e>^3,G6(81)<srbo>^0,H6(64)<bhbr>^0,I6(241)<gush>^0,J6(201)<uhnp>^3,K6(66)<nnbr>^2,L6(137)<tgrr>^0,M6(189)<csng>^0,N6(210)<kscg>^2,O6(176)<gsfl>^3,P6(8)<fm*a>^3,G7(233)<stss>^0,H7(88)<bubt>^0,I7(172)<ukfg>^3,J7(159)<hfrt>^2,K7(90)<dpbt>^0,L7(113)<tpjc>^2,M7(207)<vgcc>^0,N7(70)<cgbc>^2,O7(118)<cujs>^3,P7(51)<ji*m>^3,F8(98)<thbv>^0,G8(228)<shkd>^2,H8(82)<rrbd>^0,I8(139)<fkrf>^1,J8(140)<flrf>^0,K8(218)<dlcp>^2,L8(130)<thjp>^0,M8(69)<vhbr>^2,N8(65)<rvbr>^0,O8(195)<uvnl>^2,P8(22)<la*i>^3,A9(25)<ua*i>^1,B9(221)<uucv>^3,C9(222)<uvcv>^1,D9(219)<kdcu>^0,E9(145)<cdrn>^2,F9(199)<ttnt>^1,G9(229)<gvkt>^0,H9(164)<dprv>^0,I9(109)<pkjf>^3,J9(127)<nfjp>^1,K9(200)<scnh>^1,L9(236)<gtsd>^1,M9(79)<tcbg>^0,N9(148)<cnrc>^0,O9(183)<shnn>^0,P9(12)<he*a>^3,A10(11)<oi*a>^1,B10(250)<puot>^1,C10(117)<vpjk>^2,D10(152)<kkrg>^2,E10(154)<vprg>^0,F10(171)<tpfg>^2,G10(155)<ggrd>^2,H10(251)<vhdd>^0,I10(75)<hcbk>^3,J10(78)<cpbg>^1,K10(213)<hhcd>^1,L10(170)<dhfg>^2,M10(224)<tgkk>^2,N10(209)<hock>^0,O10(77)<sobs>^2,P10(41)<sq*e>^3,A11(7)<fa*a>^1,B11(122)<fpjt>^3,C11(104)<vfjj>^0,D11(141)<surf>^0,E11(256)<uvhv>^3,F11(178)<lpfh>^0,G11(162)<ntrp>^0,H11(245)<vtgd>^2,I11(165)<cdfn>^2,J11(202)<vgnp>^1,K11(151)<dvrs>^2,L11(107)<shjf>^3,M11(116)<lkjk>^1,N11(252)<hldl>^2,O11(87)<ptbl>^0,P11(32)<tq*q>^3,A12(24)<ta*i>^1,B12(254)<uptp>^1,C12(216)<vucl>^2,D12(185)<slnk>^2,E12(134)<kdjv>^3,F12(115)<gljk>^1,G12(190)<psng>^0,H12(226)<sokg>^3,I12(150)<fkrs>^2,J12(238)<dpsl>^1,K12(157)<vgrd>^0,L12(244)<thgo>^1,M12(74)<tobk>^3,N12(93)<sdbh>^1,O12(128)<sujp>^3,P12(28)<jq*q>^3,A13(40)<si*e>^1,B13(103)<psjj>^2,C13(129)<dcjp>^1,D13(166)<dhfn>^3,E13(177)<ndft>^1,F13(114)<ndjk>^3,G13(133)<npjv>^1,H13(196)<vonl>^1,I13(147)<rvrc>^2,J13(214)<ctcl>^3,K13(215)<dvcl>^1,L13(248)<ldod>^0,M13(73)<odbk>^2,N13(91)<klbh>^3,O13(100)<vubv>^1,P13(36)<ve*q>^3,A14(21)<de*i>^1,B14(121)<nvjd>^0,C14(255)<pvtv>^2,D14(120)<hvjo>^2,E14(239)<ovst>^3,F14(234)<pdsg>^1,G14(136)<ptjv>^3,H14(119)<pljg>^1,I14(161)<ftrp>^0,J14(124)<tojt>^3,K14(110)<oljn>^1,L14(237)<losd>^2,M14(83)<kdbd>^0,N14(249)<duol>^3,O14(163)<okrv>^3,P14(37)<ra*e>^3,A15(31)<oi*q>^1,B15(76)<nobs>^2,C15(112)<tsjc>^2,D15(63)<jcbj>^2,E15(125)<lvjh>^1,F15(227)<llkg>^3,G15(231)<ltkh>^1,H15(156)<glrd>^2,I15(108)<dojf>^3,J15(126)<uojh>^1,K15(206)<vunu>^0,L15(187)<ugns>^3,M15(72)<nrbk>^3,N15(80)<pubg>^1,O15(225)<pokk>^3,P15(9)<kq*a>^3,A16(1)<aq**>^1,B16(5)<ba*a>^2,C16(15)<ja*i>^2,D16(26)<bi*q>^2,E16(56)<hq*m>^2,F16(23)<lm*i>^2,G16(33)<hi*q>^2,H16(29)<rq*q>^2,I16(44)<oq*e>^2,J16(34)<he*q>^2,K16(60)<vq*m>^2,L16(30)<gm*q>^2,M16(16)<rq*i>^2,N16(19)<gi*i>^2,O16(20)<oi*i>^2,P16(4)<qi**>^2",
  "createTS" : 1528216217193,
  "absoluteLevel" : 207
}